README.md
vditor/configs.py
vditor/fields.py
vditor/static/dist/css/content-theme/ant-design.css
vditor/static/dist/css/content-theme/dark.css
vditor/static/dist/css/content-theme/light.css
vditor/static/dist/css/content-theme/wechat.css
vditor/static/dist/images/emoji/b3log.png
vditor/static/dist/images/emoji/chainbook.png
vditor/static/dist/images/emoji/doge.png
vditor/static/dist/images/emoji/hacpai.png
vditor/static/dist/images/emoji/huaji.gif
vditor/static/dist/images/emoji/latke.png
vditor/static/dist/images/emoji/liandi.png
vditor/static/dist/images/emoji/lute.png
vditor/static/dist/images/emoji/octocat.png
vditor/static/dist/images/emoji/pipe.png
vditor/static/dist/images/emoji/siyuan.png
vditor/static/dist/images/emoji/solo.png
vditor/static/dist/images/emoji/sym.png
vditor/static/dist/images/emoji/trollface.png
vditor/static/dist/images/emoji/vditor.png
vditor/static/dist/images/emoji/wide.png
vditor/static/dist/images/emoji/wulian.png
vditor/static/dist/images/img-loading.svg
vditor/static/dist/images/logo.png
vditor/static/dist/index.css
vditor/static/dist/index.d.ts
vditor/static/dist/index.js
vditor/static/dist/index.min.js
vditor/static/dist/js/abcjs/abcjs_basic.min.js
vditor/static/dist/js/echarts/echarts.min.js
vditor/static/dist/js/flowchart.js/flowchart.min.js
vditor/static/dist/js/graphviz/full.render.js
vditor/static/dist/js/graphviz/viz.js
vditor/static/dist/js/highlight.js/LICENSE
vditor/static/dist/js/highlight.js/highlight.min.js
vditor/static/dist/js/highlight.js/styles/a11y-dark.min.css
vditor/static/dist/js/highlight.js/styles/a11y-light.min.css
vditor/static/dist/js/highlight.js/styles/agate.min.css
vditor/static/dist/js/highlight.js/styles/an-old-hope.min.css
vditor/static/dist/js/highlight.js/styles/androidstudio.min.css
vditor/static/dist/js/highlight.js/styles/ant-design.min.css
vditor/static/dist/js/highlight.js/styles/arduino-light.min.css
vditor/static/dist/js/highlight.js/styles/arta.min.css
django_vditor_v3-2.0.3.dist-info/WHEEL
django_vditor_v3-2.0.3.dist-info/METADATA
django_vditor_v3-2.0.3.dist-info/licenses/LICENSE
django_vditor_v3-2.0.3.dist-info/RECORD
