Metadata-Version: 2.1
Name: django-vditor-v3
Version: 2.0.3
Summary: A WYSIWYG editor plugin made by vditor for django
License: MIT
Keywords: django,editor,django-application
Author-email: mircool <ynyjyz@163.com>,pi-dal <hi@pi-dal.com>
Requires-Python: >=3.8
Requires-Dist: django<6.0,>=2.2
Project-URL: Documentation, https://github.com/mircool/django-vditor-v3/blob/main/README.md
Project-URL: Homepage, https://pypi.org/project/django-vditor-v3
Project-URL: Repository, https://github.com/mircool/django-vditor-v3
